MANIFEST.in
README.rst
setup.py
bin/rsm
raw_sql_migrate/__init__.py
raw_sql_migrate/api.py
raw_sql_migrate/cli.py
raw_sql_migrate/exceptions.py
raw_sql_migrate/helpers.py
raw_sql_migrate/migration.py
raw_sql_migrate.egg-info/PKG-INFO
raw_sql_migrate.egg-info/SOURCES.txt
raw_sql_migrate.egg-info/dependency_links.txt
raw_sql_migrate.egg-info/top_level.txt
raw_sql_migrate/engines/__init__.py
raw_sql_migrate/engines/base.py
raw_sql_migrate/engines/mysql.py
raw_sql_migrate/engines/postgresql_psycopg2.py