Metadata-Version: 1.1
Name: raw-sql-migrate
Version: 0.3.4
Summary: Simple tool for managing raw sql migrations scripts.
Home-page: https://github.com/ts-taiye/raw-sql-migrate
Author: Vadim Tsander
Author-email: ts.taiye@live.com
License: UNKNOWN
Platform: UNKNOWN
Classifier: Development Status :: 4 - Beta
Classifier: Environment :: Web Environment
Classifier: Intended Audience :: Developers
Classifier: Natural Language :: English
Classifier: License :: OSI Approved :: BSD License
Classifier: Operating System :: OS Independent
Classifier: Programming Language :: Python
Classifier: Programming Language :: Python :: 2.6
Classifier: Programming Language :: Python :: 2.7
Classifier: Topic :: Software Development :: Libraries :: Python Modules
